djinx/__init__.py
djinx-0.0.1.dist-info/METADATA
djinx-0.0.1.dist-info/WHEEL
djinx-0.0.1.dist-info/top_level.txt
djinx-0.0.1.dist-info/RECORD
